utillc/__init__.py
utillc/expression.py
utillc/inctest.py
utillc/parsetab.py
utillc/qtp.py
utillc/utillc.py
utillc-0.11.2.dist-info/METADATA
utillc-0.11.2.dist-info/WHEEL
utillc-0.11.2.dist-info/top_level.txt
utillc-0.11.2.dist-info/RECORD
