Metadata-Version: 2.1
Name: utillc
Version: 0.11.2
Summary: a utility for smart logging
Author: ClovisHeaulier
Author-email: clovis.heaulier@gmail.com
License: MIT
Keywords: logging fstring alternative
Requires-Python: >=2.7
Requires-Dist: numpy>=1.19
Requires-Dist: ply>=3.11
Requires-Dist: Pillow>=10.3
